PhpKuozhanKaifaJiNeiheYingyong/README.md
PhpKuozhanKaifaJiNeiheYingyong/__init__.py
PhpKuozhanKaifaJiNeiheYingyong/__main__.py
PhpKuozhanKaifaJiNeiheYingyong/file.epub
PhpKuozhanKaifaJiNeiheYingyong/index.html
PhpKuozhanKaifaJiNeiheYingyong/css/__init__.py
PhpKuozhanKaifaJiNeiheYingyong/css/annotations.css
PhpKuozhanKaifaJiNeiheYingyong/css/main.css
PhpKuozhanKaifaJiNeiheYingyong/css/normalize.css
PhpKuozhanKaifaJiNeiheYingyong/css/popup.css
PhpKuozhanKaifaJiNeiheYingyong/font/__init__.py
PhpKuozhanKaifaJiNeiheYingyong/font/fontello.eot
PhpKuozhanKaifaJiNeiheYingyong/font/fontello.svg
PhpKuozhanKaifaJiNeiheYingyong/font/fontello.ttf
PhpKuozhanKaifaJiNeiheYingyong/font/fontello.woff
PhpKuozhanKaifaJiNeiheYingyong/img/__init__.py
PhpKuozhanKaifaJiNeiheYingyong/img/annotator-glyph-sprite.png
PhpKuozhanKaifaJiNeiheYingyong/img/annotator-icon-sprite.png
PhpKuozhanKaifaJiNeiheYingyong/img/apple-touch-icon.png
PhpKuozhanKaifaJiNeiheYingyong/img/cancelfullscreen.png
PhpKuozhanKaifaJiNeiheYingyong/img/close.png
PhpKuozhanKaifaJiNeiheYingyong/img/fullscreen.png
PhpKuozhanKaifaJiNeiheYingyong/img/loader.gif
PhpKuozhanKaifaJiNeiheYingyong/img/menu-icon.png
PhpKuozhanKaifaJiNeiheYingyong/img/save.png
PhpKuozhanKaifaJiNeiheYingyong/img/saved.png
PhpKuozhanKaifaJiNeiheYingyong/img/settings-s.png
PhpKuozhanKaifaJiNeiheYingyong/img/settings.png
PhpKuozhanKaifaJiNeiheYingyong/img/star.png
PhpKuozhanKaifaJiNeiheYingyong/js/__init__.py
PhpKuozhanKaifaJiNeiheYingyong/js/epub.js
PhpKuozhanKaifaJiNeiheYingyong/js/epub.min.js
PhpKuozhanKaifaJiNeiheYingyong/js/epub.min.map
PhpKuozhanKaifaJiNeiheYingyong/js/hooks.min.js
PhpKuozhanKaifaJiNeiheYingyong/js/hooks.min.map
PhpKuozhanKaifaJiNeiheYingyong/js/reader.js
PhpKuozhanKaifaJiNeiheYingyong/js/reader.js.map
PhpKuozhanKaifaJiNeiheYingyong/js/reader.min.js
PhpKuozhanKaifaJiNeiheYingyong/js/reader.min.map
PhpKuozhanKaifaJiNeiheYingyong/js/hooks/__init__.py
PhpKuozhanKaifaJiNeiheYingyong/js/hooks/extensions/__init__.py
php_kuozhan_kaifa_ji_neihe_yingyong-2024.3.1.0.dist-info/METADATA
php_kuozhan_kaifa_ji_neihe_yingyong-2024.3.1.0.dist-info/WHEEL
php_kuozhan_kaifa_ji_neihe_yingyong-2024.3.1.0.dist-info/entry_points.txt
php_kuozhan_kaifa_ji_neihe_yingyong-2024.3.1.0.dist-info/top_level.txt
php_kuozhan_kaifa_ji_neihe_yingyong-2024.3.1.0.dist-info/RECORD
